rizallogger/__init__.py
rizallogger-0.1.0.dist-info/LICENSE
rizallogger-0.1.0.dist-info/METADATA
rizallogger-0.1.0.dist-info/WHEEL
rizallogger-0.1.0.dist-info/RECORD
