Metadata-Version: 2.1
Name: rizallogger
Version: 0.1.0
Summary: Make easy to log your project
License: MIT
Author: Safrizal
Requires-Python: >=3.10,<4.0
Classifier: License :: OSI Approved :: MIT License
Classifier: Operating System :: OS Independent
Classifier: Programming Language :: Python :: 3
Classifier: Programming Language :: Python :: 3.10
Classifier: Programming Language :: Python :: 3.11
Requires-Dist: setuptools (>=68.0.0,<69.0.0)
Requires-Dist: tqdm (>=4.65.0,<5.0.0)
Requires-Dist: wheel (>=0.40.0,<0.41.0)
